pyams_zfiles/__init__.py
pyams_zfiles/document.py
pyams_zfiles/extractor.py
pyams_zfiles/folder.py
pyams_zfiles/include.py
pyams_zfiles/index.py
pyams_zfiles/interfaces.py
pyams_zfiles/layer.py
pyams_zfiles/monitor.py
pyams_zfiles/search.py
pyams_zfiles/synchronizer.py
pyams_zfiles/utility.py
pyams_zfiles/workflow.py
pyams_zfiles/api/__init__.py
pyams_zfiles/api/graph.py
pyams_zfiles/api/rest.py
pyams_zfiles/api/rpc.py
pyams_zfiles/doctests/README.rst
pyams_zfiles/doctests/data/document.txt
pyams_zfiles/generations/__init__.py
pyams_zfiles/generations/evolve1.py
pyams_zfiles/generations/evolve2.py
pyams_zfiles/locales/pyams_zfiles.pot
pyams_zfiles/locales/fr/LC_MESSAGES/pyams_zfiles.mo
pyams_zfiles/locales/fr/LC_MESSAGES/pyams_zfiles.po
pyams_zfiles/skin/__init__.py
pyams_zfiles/skin/container.py
pyams_zfiles/skin/file.py
pyams_zfiles/task/__init__.py
pyams_zfiles/task/interfaces.py
pyams_zfiles/task/zmi/__init__.py
pyams_zfiles/tests/__init__.py
pyams_zfiles/tests/test_utilsdocs.py
pyams_zfiles/tests/test_utilsdocstrings.py
pyams_zfiles/zmi/__init__.py
pyams_zfiles/zmi/document.py
pyams_zfiles/zmi/extractor.py
pyams_zfiles/zmi/index.py
pyams_zfiles/zmi/interfaces.py
pyams_zfiles/zmi/properties.py
pyams_zfiles/zmi/search.py
pyams_zfiles/zmi/synchronizer.py
pyams_zfiles/zmi/workflow.py
pyams_zfiles/zmi/templates/properties-display.pt
pyams_zfiles-2.8.0.dist-info/LICENSE
pyams_zfiles-2.8.0.dist-info/METADATA
pyams_zfiles-2.8.0.dist-info/WHEEL
pyams_zfiles-2.8.0.dist-info/namespace_packages.txt
pyams_zfiles-2.8.0.dist-info/top_level.txt
pyams_zfiles-2.8.0.dist-info/RECORD
