Metadata-Version: 2.1
Name: pyams-zfiles
Version: 2.8.0
Summary: PyAMS files storage manager
Home-page: https://pyams.readthedocs.io
Author: Thierry Florac
Author-email: tflorac@ulthar.net
License: ZPL
Keywords: Pyramid PyAMS
Classifier: License :: OSI Approved :: Zope Public License
Classifier: Development Status :: 4 - Beta
Classifier: Programming Language :: Python
Classifier: Framework :: Pyramid
Classifier: Topic :: Software Development :: Libraries :: Python Modules
License-File: LICENSE
Requires-Dist: setuptools
Requires-Dist: colander
Requires-Dist: cornice
Requires-Dist: cornice-swagger
Requires-Dist: graphene
Requires-Dist: hypatia
Requires-Dist: persistent
Requires-Dist: pyams-catalog
Requires-Dist: pyams-file >=2.4.0
Requires-Dist: pyams-form
Requires-Dist: pyams-layer
Requires-Dist: pyams-security >=1.10.5
Requires-Dist: pyams-site
Requires-Dist: pyams-skin >=2.4.0
Requires-Dist: pyams-utils >=2.8.0
Requires-Dist: pyams-workflow >=2.2.0
Requires-Dist: pypdf
Requires-Dist: pyramid >=2.0.0
Requires-Dist: pyramid-rpc
Requires-Dist: python-dateutil
Requires-Dist: zope.container
Requires-Dist: zope.copy
Requires-Dist: zope.dublincore
Requires-Dist: zope.interface
Requires-Dist: zope.intid
Requires-Dist: zope.lifecycleevent
Requires-Dist: zope.location
Requires-Dist: zope.schema
Requires-Dist: zope.traversing
Provides-Extra: test
Requires-Dist: pyams-alchemy ; extra == 'test'
Requires-Dist: pyams-form ; extra == 'test'
Requires-Dist: pyams-pagelet ; extra == 'test'
Requires-Dist: pyams-scheduler >=2.7.0 ; extra == 'test'
Requires-Dist: pyams-skin ; extra == 'test'
Requires-Dist: pyams-table ; extra == 'test'
Requires-Dist: pyams-viewlet ; extra == 'test'
Requires-Dist: pyams-zmi ; extra == 'test'
Requires-Dist: pyramid-zcml ; extra == 'test'
Requires-Dist: zope.exceptions ; extra == 'test'
